README.md
setup.py
Flask_PubSubDecorator.egg-info/PKG-INFO
Flask_PubSubDecorator.egg-info/SOURCES.txt
Flask_PubSubDecorator.egg-info/dependency_links.txt
Flask_PubSubDecorator.egg-info/requires.txt
Flask_PubSubDecorator.egg-info/top_level.txt
PubSubDecorator/__init__.py