Metadata-Version: 1.0
Name: Flask-PubSubDecorator
Version: 0.0.5
Summary: Decorates publisher functions and subscriber routes creating topics/subscriptions if necessary
Home-page: https://github.com/MobiusWorksLLC/Flask-PubSubDecorator.git
Author: Tyson Holub
Author-email: tholub@mobiusworks.com
License: MIT
Platform: UNKNOWN
